django_channels_router/__init__.py
django_channels_router/async_socket_router.py
django_channels_router/socket_router.py
django_channels_router/tools.py
django_channels_router/classes/__init__.py
django_channels_router/classes/abstract_socket_router.py
django_channels_router/classes/message.py
django_channels_router/classes/route_info.py
django_channels_router/classes/socket_result.py
django_channels_router/classes/status.py
django_channels_router-1.0.3.dist-info/METADATA
django_channels_router-1.0.3.dist-info/WHEEL
django_channels_router-1.0.3.dist-info/licenses/LICENSE
django_channels_router-1.0.3.dist-info/RECORD
