Metadata-Version: 2.4
Name: django-channels-router
Version: 1.0.3
Summary: HTTP-style WebSocket routing for Django Channels.
Project-URL: Homepage, https://github.com/Alireza-Tabatabaeian/django-channels-router
Project-URL: Documentation, https://github.com/Alireza-Tabatabaeian/django-channels-router
Project-URL: Source, https://github.com/Alireza-Tabatabaeian/django-channels-router
Project-URL: Issues, https://github.com/Alireza-Tabatabaeian/django-channels-router/issues
Author-email: Alireza Tabatabaeian <alireza.tabatabaeian@gmail.com>
Maintainer-email: Alireza Tabatabaeian <alireza.tabatabaeian@gmail.com>
License-File: LICENSE
Keywords: async,channels,django,observable-socket,real-time,router,websocket
Classifier: Development Status :: 5 - Production/Stable
Classifier: Environment :: Web Environment
Classifier: Framework :: Django
Classifier: Framework :: Django :: 4.2
Classifier: Intended Audience :: Developers
Classifier: License :: OSI Approved :: MIT License
Classifier: Operating System :: OS Independent
Classifier: Programming Language :: Python
Classifier: Programming Language :: Python :: 3
Classifier: Programming Language :: Python :: 3.11
Classifier: Topic :: Internet :: WWW/HTTP
Classifier: Topic :: Software Development :: Libraries :: Python Modules
Requires-Python: >=3.11
Requires-Dist: channels>=4.0
Requires-Dist: django>=4.2
